{"body":"I get requests to backport Jedi Academy player models to Jedi Outcast occasionally. This could be automated.\r\n\r\nI'm not entirely sure if that's in scope of this project or should be a standalone script. If I do it in-client, there should be a way to execute it from the command line?\r\n\r\nIdeally I would be able to compile it to web assembly so I can offer it as a website without the need for uploading. ","closed":false,"comments":[],"labels":[{"id":"MDU6TGFiZWwzNDU1MTI1Nw==","name":"enhancement","description":"","color":"84b6eb"}],"milestone":{"number":1,"title":"Tools","description":"Make the game easier to mod.","dueOn":null},"projectCards":[],"projectItems":[],"state":"OPEN","title":"JA player model to JO conversion"}
